{"name":null,"assets":"aoy4:pathy46:assets%2Fsans%2Fimages%2FbattleUI%2Fbattle.pngy4:sizei17303y4:typey5:IMAGEy2:idR1y7:preloadtgoR0y42:assets%2Fsans%2Fimages%2FbattleUI%2Fbg.pngR2i1501R3R4R5R7R6tgoR0y37:assets%2Fsans%2Fimages%2FCardodge.pngR2i267530R3R4R5R8R6tgoR0y37:assets%2Fsans%2Fimages%2FCardodge.xmlR2i7401R3y4:TEXTR5R9R6tgoR0y39:assets%2Fsans%2Fimages%2FDodgeMechs.pngR2i264267R3R4R5R11R6tgoR0y39:assets%2Fsans%2Fimages%2FDodgeMechs.xmlR2i7957R3R10R5R12R6tgoR0y48:assets%2Fsans%2Fimages%2FDodgeMechsBS-Shader.pngR2i241291R3R4R5R13R6tgoR0y48:assets%2Fsans%2Fimages%2FDodgeMechsBS-Shader.xmlR2i10341R3R10R5R14R6tgoR0y37:assets%2Fsans%2Fimages%2Fgameover.pngR2i986R3R4R5R15R6tgoR0y45:assets%2Fsans%2Fimages%2FGaster_blasterss.pngR2i432422R3R4R5R16R6tgoR0y45:assets%2Fsans%2Fimages%2FGaster_blasterss.xmlR2i6736R3R10R5R17R6tgoR0y33:assets%2Fsans%2Fimages%2Fhall.pngR2i119070R3R4R5R18R6tgoR0y37:assets%2Fsans%2Fimages%2Fhalldark.pngR2i88702R3R4R5R19R6tgoR0y34:assets%2Fsans%2Fimages%2Fheart.pngR2i492R3R4R5R20R6tgoR0y53:assets%2Fsans%2Fimages%2FNightmare%20Sans%20Stage.pngR2i1615779R3R4R5R21R6tgoR0y53:assets%2Fsans%2Fimages%2FNightmare%20Sans%20Stage.xmlR2i2715R3R10R5R22R6tgoR0y34:assets%2Fsans%2Fimages%2Fsands.pngR2i57730R3R4R5R23R6tgoR0y41:assets%2Fsans%2Fimages%2FSans_Shit_NM.pngR2i215573R3R4R5R24R6tgoR0y41:assets%2Fsans%2Fimages%2FSans_Shit_NM.xmlR2i13155R3R10R5R25R6tgoR0y42:assets%2Fsans%2Fimages%2FSans_Text_box.pngR2i34989R3R4R5R26R6tgoR0y42:assets%2Fsans%2Fimages%2FSans_Text_box.xmlR2i58724R3R10R5R27R6tgoR0y37:assets%2Fsans%2Fimages%2FSoul_ded.pngR2i62576R3R4R5R28R6tgoR0y37:assets%2Fsans%2Fimages%2FSoul_ded.xmlR2i9592R3R10R5R29R6tgoR0y36:assets%2Fsans%2Fimages%2Funknown.pngR2i15826R3R4R5R30R6tgoR0y38:assets%2Fsans%2Fimages%2FWaterfall.pngR2i509708R3R4R5R31R6tgoR2i452377R3y5:SOUNDR5y38:assets%2Fsans%2Fmusic%2Ffuck%20you.oggy9:pathGroupaR33hR6tgoR2i452223R3R32R5y42:assets%2Fsans%2Fmusic%2Fgameovernormal.oggR34aR35hR6tgoR2i998286R3R32R5y33:assets%2Fsans%2Fmusic%2Fpause.oggR34aR36hR6tgoR2i7936R3R32R5y47:assets%2Fsans%2Fsounds%2Fcountdown%20finish.oggR34aR37hR6tgoR2i5437R3R32R5y38:assets%2Fsans%2Fsounds%2Fcountdown.oggR34aR38hR6tgoR2i11774R3R32R5y34:assets%2Fsans%2Fsounds%2Fdodge.oggR34aR39hR6tgoR2i12879R3R32R5y32:assets%2Fsans%2Fsounds%2Feye.oggR34aR40hR6tgoR2i9936R3R32R5y37:assets%2Fsans%2Fsounds%2Fgenocide.oggR34aR41hR6tgoR2i7420R3R32R5y33:assets%2Fsans%2Fsounds%2Fhurt.oggR34aR42hR6tgoR2i4797R3R32R5y33:assets%2Fsans%2Fsounds%2Fmove.oggR34aR43hR6tgoR2i9554R3R32R5y35:assets%2Fsans%2Fsounds%2Fnotice.oggR34aR44hR6tgoR2i8159R3R32R5y33:assets%2Fsans%2Fsounds%2Fping.oggR34aR45hR6tgoR2i17408R3R32R5y37:assets%2Fsans%2Fsounds%2Freadygas.oggR34aR46hR6tgoR2i20628R3R32R5y36:assets%2Fsans%2Fsounds%2Frimshot.oggR34aR47hR6tgoR2i11545R3R32R5y39:assets%2Fsans%2Fsounds%2Fsansattack.oggR34aR48hR6tgoR2i7808R3R32R5y35:assets%2Fsans%2Fsounds%2Fselect.oggR34aR49hR6tgoR2i24655R3R32R5y37:assets%2Fsans%2Fsounds%2Fshootgas.oggR34aR50hR6tgoR2i5486R3R32R5y39:assets%2Fsans%2Fsounds%2Fsnd_txtpap.oggR34aR51hR6tgoR2i6344R3R32R5y40:assets%2Fsans%2Fsounds%2Fsnd_txtsans.oggR34aR52hR6tgoR2i14774R3R32R5y35:assets%2Fsans%2Fsounds%2FThrow1.oggR34aR53hR6tgoR2i15391R3R32R5y35:assets%2Fsans%2Fsounds%2FThrow2.oggR34aR54hR6tgoR2i15251R3R32R5y35:assets%2Fsans%2Fsounds%2FThrow3.oggR34aR55hR6tgoR2i56800R3R32R5y36:assets%2Fsans%2Fsounds%2Ftrolled.oggR34aR56hR6tgoR2i13132R3R32R5y34:assets%2Fsans%2Fsounds%2FutDie.oggR34aR57hR6tgh","rootPath":"../","version":2,"libraryArgs":[],"libraryType":null}